HARPGraph2/__init__.py
HARPGraph2/pseudodigraph.py
HARPGraph2-0.1.0.dist-info/LICENSE
HARPGraph2-0.1.0.dist-info/METADATA
HARPGraph2-0.1.0.dist-info/WHEEL
HARPGraph2-0.1.0.dist-info/top_level.txt
HARPGraph2-0.1.0.dist-info/RECORD
