Metadata-Version: 2.1
Name: HARPGraph2
Version: 0.1.0
Summary: A generalized graph library for dealing with generalized graph structures.
Home-page: https://github.com/HARP-research-Inc/HARPGraph2
Author: Harper Chisari
Author-email: harper.chisari@harpresearch.ai
License: UNKNOWN
Platform: UNKNOWN
Classifier: Programming Language :: Python :: 3
Classifier: License :: OSI Approved :: MIT License
Classifier: Operating System :: OS Independent
Requires-Python: >=3.6
License-File: LICENSE
Requires-Dist: numpy
Requires-Dist: networkx
Requires-Dist: matplotlib
